{
  "Base-white": {
    "value": "#ffffff",
    "type": "color",
    "parent": "Premitive/Mode 1",
    "description": ""
  },
  "Base-black": {
    "value": "#1a1e22",
    "type": "color",
    "parent": "Premitive/Mode 1",
    "description": "",
    "oldValue": "#121212"
  },
  "Gray 10": {
    "value": "#fbfcfd",
    "type": "color",
    "parent": "Premitive/Mode 1",
    "description": ""
  },
  "Gray 20": {
    "value": "#edf2f7",
    "type": "color",
    "parent": "Premitive/Mode 1",
    "description": ""
  },
  "Gray 30": {
    "value": "#e1e7ed",
    "type": "color",
    "parent": "Premitive/Mode 1",
    "description": ""
  },
  "Gray 40": {
    "value": "#e2e8f0",
    "type": "color",
    "parent": "Premitive/Mode 1",
    "description": ""
  },
  "Gray 50": {
    "value": "#cbd5e0",
    "type": "color",
    "parent": "Premitive/Mode 1",
    "description": ""
  },
  "Gray 60": {
    "value": "#3f4a55",
    "type": "color",
    "parent": "Premitive/Mode 1",
    "description": "",
    "oldValue": "#a0aec0"
  },
  "Gray 70": {
    "value": "#343a42",
    "type": "color",
    "parent": "Premitive/Mode 1",
    "description": "",
    "oldValue": "#718096"
  },
  "Gray 80": {
    "value": "#2a2f35",
    "type": "color",
    "parent": "Premitive/Mode 1",
    "description": "",
    "oldValue": "#4a5568"
  },
  "Gray 90": {
    "value": "#21262b",
    "type": "color",
    "parent": "Premitive/Mode 1",
    "description": "",
    "oldValue": "#2d3748"
  },
  "Gray 100": {
    "value": "#14171a",
    "type": "color",
    "parent": "Premitive/Mode 1",
    "description": "",
    "oldValue": "#1a202c"
  },
  "Brand-primary 10": {
    "value": "#f1fafe",
    "type": "color",
    "parent": "Premitive/Mode 1",
    "description": ""
  },
  "Brand-secondary 60 (Base)": {
    "value": "#004c70",
    "type": "color",
    "parent": "Premitive/Mode 1",
    "description": ""
  },
  "Brand-tertiary 1": {
    "value": "#212b36",
    "type": "color",
    "parent": "Premitive/Mode 1",
    "description": ""
  },
  "Brand-tertiary 2": {
    "value": "#e5e5e5",
    "type": "color",
    "parent": "Premitive/Mode 1",
    "description": ""
  },
  "Error 10": {
    "value": "#6e1d12",
    "type": "color",
    "parent": "Premitive/Mode 1",
    "description": ""
  },
  "Error 30": {
    "value": "#ee3e29",
    "type": "color",
    "parent": "Premitive/Mode 1",
    "description": ""
  },
  "Error 40": {
    "value": "#f06354",
    "type": "color",
    "parent": "Premitive/Mode 1",
    "description": ""
  },
  "Warning 10": {
    "value": "#c6920e",
    "type": "color",
    "parent": "Premitive/Mode 1",
    "description": ""
  },
  "Warning 30": {
    "value": "#fce86b",
    "type": "color",
    "parent": "Premitive/Mode 1",
    "description": ""
  },
  "Warning 40": {
    "value": "#fded87",
    "type": "color",
    "parent": "Premitive/Mode 1",
    "description": ""
  },
  "Success 10": {
    "value": "#085d3a",
    "type": "color",
    "parent": "Premitive/Mode 1",
    "description": ""
  },
  "Success 30": {
    "value": "#0fb949",
    "type": "color",
    "parent": "Premitive/Mode 1",
    "description": ""
  },
  "Success 40": {
    "value": "#7cdebd",
    "type": "color",
    "parent": "Premitive/Mode 1",
    "description": ""
  },
  "Accent Blue 10": {
    "value": "#110070",
    "type": "color",
    "parent": "Premitive/Mode 1",
    "description": ""
  },
  "Accent Blue 20": {
    "value": "#1c00ad",
    "type": "color",
    "parent": "Premitive/Mode 1",
    "description": ""
  },
  "Accent Blue 30": {
    "value": "#2600ee",
    "type": "color",
    "parent": "Premitive/Mode 1",
    "description": ""
  },
  "Accent Blue 40": {
    "value": "#5133f2",
    "type": "color",
    "parent": "Premitive/Mode 1",
    "description": ""
  },
  "Accent Blue 50": {
    "value": "#7d66f5",
    "type": "color",
    "parent": "Premitive/Mode 1",
    "description": ""
  },
  "Accent Orange 10": {
    "value": "#7d4a05",
    "type": "color",
    "parent": "Premitive/Mode 1",
    "description": ""
  },
  "Accent Orange 20": {
    "value": "#ba710a",
    "type": "color",
    "parent": "Premitive/Mode 1",
    "description": ""
  },
  "Accent Orange 30": {
    "value": "#fa960e",
    "type": "color",
    "parent": "Premitive/Mode 1",
    "description": ""
  },
  "Accent Orange 40": {
    "value": "#fdaa3d",
    "type": "color",
    "parent": "Premitive/Mode 1",
    "description": ""
  },
  "Accent Orange 50": {
    "value": "#fcc26e",
    "type": "color",
    "parent": "Premitive/Mode 1",
    "description": ""
  },
  "Error 20": {
    "value": "#ae2e1e",
    "type": "color",
    "parent": "Premitive/Mode 1",
    "description": ""
  },
  "Error 50": {
    "value": "#ffebe9",
    "type": "color",
    "parent": "Premitive/Mode 1",
    "description": ""
  },
  "Warning 20": {
    "value": "#fbe142",
    "type": "color",
    "parent": "Premitive/Mode 1",
    "description": ""
  },
  "Warning 50": {
    "value": "#fffbe5",
    "type": "color",
    "parent": "Premitive/Mode 1",
    "description": ""
  },
  "Success 20": {
    "value": "#289771",
    "type": "color",
    "parent": "Premitive/Mode 1",
    "description": ""
  },
  "Success 50": {
    "value": "#eafff8",
    "type": "color",
    "parent": "Premitive/Mode 1",
    "description": ""
  },
  "Brand-primary 50": {
    "value": "#88d6ed",
    "type": "color",
    "parent": "Premitive/Mode 1",
    "description": ""
  },
  "Brand-primary 40": {
    "value": "#a0def1",
    "type": "color",
    "parent": "Premitive/Mode 1",
    "description": ""
  },
  "Brand-primary 30": {
    "value": "#cfeff8",
    "type": "color",
    "parent": "Premitive/Mode 1",
    "description": ""
  },
  "Brand-primary 20": {
    "value": "#e2f5fb",
    "type": "color",
    "parent": "Premitive/Mode 1",
    "description": ""
  },
  "Brand-primary 60 (Base)": {
    "value": "#70ceea",
    "type": "color",
    "parent": "Premitive/Mode 1",
    "description": ""
  },
  "Brand-primary 70": {
    "value": "#5dacc3",
    "type": "color",
    "parent": "Premitive/Mode 1",
    "description": ""
  },
  "Brand-primary 80": {
    "value": "#4b899c",
    "type": "color",
    "parent": "Premitive/Mode 1",
    "description": ""
  },
  "Brand-primary 90": {
    "value": "#386775",
    "type": "color",
    "parent": "Premitive/Mode 1",
    "description": ""
  },
  "Brand-primary 100": {
    "value": "#25454e",
    "type": "color",
    "parent": "Premitive/Mode 1",
    "description": ""
  },
  "Brand-secondary 10": {
    "value": "#f5f5f5",
    "type": "color",
    "parent": "Premitive/Mode 1",
    "description": ""
  },
  "Brand-secondary 20": {
    "value": "#cfe0e9",
    "type": "color",
    "parent": "Premitive/Mode 1",
    "description": ""
  },
  "Brand-secondary 30": {
    "value": "#80a5b7",
    "type": "color",
    "parent": "Premitive/Mode 1",
    "description": ""
  },
  "Brand-secondary 40": {
    "value": "#5588a0",
    "type": "color",
    "parent": "Premitive/Mode 1",
    "description": ""
  },
  "Brand-secondary 50": {
    "value": "#2b6a88",
    "type": "color",
    "parent": "Premitive/Mode 1",
    "description": ""
  },
  "Brand-secondary 70": {
    "value": "#003f5d",
    "type": "color",
    "parent": "Premitive/Mode 1",
    "description": ""
  },
  "Brand-secondary 80": {
    "value": "#00334b",
    "type": "color",
    "parent": "Premitive/Mode 1",
    "description": ""
  },
  "Brand-secondary 90": {
    "value": "#002638",
    "type": "color",
    "parent": "Premitive/Mode 1",
    "description": ""
  },
  "Brand-secondary 100": {
    "value": "#001925",
    "type": "color",
    "parent": "Premitive/Mode 1",
    "description": ""
  },
  "Info 10": {
    "value": "#e6f1ff",
    "type": "color",
    "parent": "Premitive/Mode 1",
    "description": ""
  },
  "Info 20": {
    "value": "#6bafff",
    "type": "color",
    "parent": "Premitive/Mode 1",
    "description": ""
  },
  "Info 30": {
    "value": "#4294f4",
    "type": "color",
    "parent": "Premitive/Mode 1",
    "description": ""
  },
  "Info 40": {
    "value": "#2f88ef",
    "type": "color",
    "parent": "Premitive/Mode 1",
    "description": ""
  },
  "Info 50": {
    "value": "#116bd5",
    "type": "color",
    "parent": "Premitive/Mode 1",
    "description": ""
  },
  "Dark Opacity 10": {
    "value": "#1a202ccc",
    "type": "color",
    "parent": "Premitive/Mode 1",
    "description": ""
  },
  "Dark Opacity 20": {
    "value": "#1a202c99",
    "type": "color",
    "parent": "Premitive/Mode 1",
    "description": ""
  },
  "Dark Opacity 30": {
    "value": "#1a202c66",
    "type": "color",
    "parent": "Premitive/Mode 1",
    "description": ""
  },
  "Dark Opacity 40": {
    "value": "#1a202c33",
    "type": "color",
    "parent": "Premitive/Mode 1",
    "description": ""
  },
  "Dark Opacity 50": {
    "value": "#1a202c0a",
    "type": "color",
    "parent": "Premitive/Mode 1",
    "description": ""
  },
  "Light Opacity 10": {
    "value": "#ffffffcc",
    "type": "color",
    "parent": "Premitive/Mode 1",
    "description": ""
  },
  "Light Opacity 20": {
    "value": "#ffffff99",
    "type": "color",
    "parent": "Premitive/Mode 1",
    "description": ""
  },
  "Light Opacity 30": {
    "value": "#ffffff66",
    "type": "color",
    "parent": "Premitive/Mode 1",
    "description": ""
  },
  "Light Opacity 40": {
    "value": "#ffffff33",
    "type": "color",
    "parent": "Premitive/Mode 1",
    "description": ""
  },
  "Light Opacity 50": {
    "value": "#ffffff0a",
    "type": "color",
    "parent": "Premitive/Mode 1",
    "description": ""
  },
  "Dark Opacity 40%": {
    "value": "#1a202c66",
    "type": "color",
    "parent": "Premitive/Mode 1",
    "description": ""
  },
  "Dark Opacity 16%": {
    "value": "#1a202c29",
    "type": "color",
    "parent": "Premitive/Mode 1",
    "description": ""
  },
  "Dark Opacity 8%": {
    "value": "#1a202c14",
    "type": "color",
    "parent": "Premitive/Mode 1",
    "description": ""
  },
  "Dark Opacity 4%": {
    "value": "#1a202c0a",
    "type": "color",
    "parent": "Premitive/Mode 1",
    "description": ""
  },
  "Dark Opacity 2%": {
    "value": "#1a202c05",
    "type": "color",
    "parent": "Premitive/Mode 1",
    "description": ""
  },
  "Light Opacity 40%": {
    "value": "#ffffff66",
    "type": "color",
    "parent": "Premitive/Mode 1",
    "description": ""
  },
  "Light Opacity 16%": {
    "value": "#ffffff29",
    "type": "color",
    "parent": "Premitive/Mode 1",
    "description": ""
  },
  "Light Opacity 8%": {
    "value": "#ffffff14",
    "type": "color",
    "parent": "Premitive/Mode 1",
    "description": ""
  },
  "Light Opacity 4%": {
    "value": "#ffffff0a",
    "type": "color",
    "parent": "Premitive/Mode 1",
    "description": ""
  },
  "Light Opacity 2%": {
    "value": "#ffffff05",
    "type": "color",
    "parent": "Premitive/Mode 1",
    "description": ""
  }
}